light_sql3.py
light_sql3-1.0.1.dist-info/WHEEL
light_sql3-1.0.1.dist-info/METADATA
light_sql3-1.0.1.dist-info/RECORD
