Metadata-Version: 2.1
Name: light-sql3
Version: 1.0.1
Summary: Light cover for sqlite3
License: MIT
Author: Forzy
Author-email: nikita11tzby@gmail.com
Requires-Python: >=3.7,<4.0
Classifier: License :: OSI Approved :: MIT License
Classifier: Programming Language :: Python :: 3
Classifier: Programming Language :: Python :: 3.10
Classifier: Programming Language :: Python :: 3.7
Classifier: Programming Language :: Python :: 3.8
Classifier: Programming Language :: Python :: 3.9
